AUTHORS
ChangeLog
LICENSE
MANIFEST.in
README.rst
jupyter_remote_tips.rst
requirements.txt
setup.cfg
setup.py
bin/jupyter-o2
example_cfgs/jupyter-remote-o2.cfg
jupyter_remote/__init__.py
jupyter_remote/__main__.py
jupyter_remote/config_manager.py
jupyter_remote/jupyter-remote.cfg
jupyter_remote/jupyter_remote.py
jupyter_remote/pysectools.py
jupyter_remote/utils.py
jupyter_remote/version.py
jupyter_remote.egg-info/PKG-INFO
jupyter_remote.egg-info/SOURCES.txt
jupyter_remote.egg-info/dependency_links.txt
jupyter_remote.egg-info/entry_points.txt
jupyter_remote.egg-info/not-zip-safe
jupyter_remote.egg-info/pbr.json
jupyter_remote.egg-info/requires.txt
jupyter_remote.egg-info/top_level.txt
tests/__init__.py
tests/test_jupyter_remote.py
tests/test_jupyter_remote_config_manager.py
tests/test_jupyter_remote_utils.py
tests/test_pysectools.py