Metadata-Version: 1.1
Name: jupyter-remote
Version: 0.9.2
Summary: Run Jupyter on a remote server
Home-page: https://github.com/AaronKollasch/jupyter-remote
Author: Aaron Kollasch
Author-email: awkollasch@gmail.com
License: MIT
Keywords: jupyter,remote,ssh,slurm,pexpect,orchestra,o2
Platform: UNKNOWN
Classifier: Development Status :: 5 - Production/Stable
Classifier: Intended Audience :: Developers
Classifier: Intended Audience :: System Administrators
Classifier: Intended Audience :: Science/Research
Classifier: Environment :: Console
Classifier: Operating System :: MacOS :: MacOS X
Classifier: Operating System :: POSIX
Classifier: Topic :: Utilities
Classifier: License :: OSI Approved :: MIT License
Classifier: Programming Language :: Python :: 2
Classifier: Programming Language :: Python :: 2.7
Classifier: Programming Language :: Python :: 3
Classifier: Programming Language :: Python :: 3.6
